.DS_Store
pyladies/__init__.py
pyladies/main.py
pyladies/logos/general/logo-magenta-1499x638.png
pyladies/logos/general/logo-magenta.svg
pyladies/logos/general/logo_300x300.png
pyladies/logos/general/logo_square.svg
pyladies/logos/general/pyladies-geek.ai
pyladies/logos/general/pyladies-logo.ai
pyladies/logos/locations/dc/logo-redblue-dc-1695x1403.png
pyladies/logos/locations/dc/logo-redblue-dc.svg
pyladies/logos/locations/la/logo-magenta-la-1695x1403.png
pyladies/logos/locations/la/logo-magenta-la.svg
pyladies/swag/flyers/poster-bitmap1.png
pyladies/swag/flyers/poster-bitmap2.png
pyladies/swag/flyers/poster-vector1.png
pyladies/swag/flyers/poster-vector2.png
pyladies/swag/flyers/poster1.svg
pyladies/swag/flyers/poster2.svg
pyladies/swag/flyers/la/la-nov2011-general.jpg
pyladies/swag/flyers/la/la-oct2011-caltech.png
pyladies/swag/flyers/la/la-oct2011-caltech.svg
pyladies/swag/PyCon 2014/PyCon2014-Back-plustrim.pdf
pyladies/swag/PyCon 2014/PyCon2014-Back.pdf
pyladies/swag/PyCon 2014/PyCon2014-Front-plustrim.pdf
pyladies/swag/PyCon 2014/PyCon2014-Front.pdf
pyladies/swag/PyCon 2014/pyladies-bizcard-back.pdf
pyladies/swag/PyCon 2014/pyladies-bizcards-front.pdf
pyladies/swag/PyCon 2014/pyladies-bizcards-plustrim.pdf
pyladies/swag/PyCon 2014/R335555751_A_proof.png
pyladies/swag/stickers/face_sticker.png
pyladies/swag/stickers/logo-sticker-1499x638.png
pyladies/swag/stickers/logo-sticker.svg
pyladies/swag/stickers/R335555751_A_proof.png
pyladies/swag/tshirts/i-love-pyladies/printing-instructions.rst
pyladies/swag/tshirts/i-love-pyladies/pyladies-tshirt.eps
pyladies/swag/tshirts/i-love-pyladies/pyladies-tshirt.jpg
pyladies/swag/tshirts/i-love-pyladies/pyladies-tshirt.pdf
pyladies/swag/tshirts/i-love-pyladies/pyladies-tshirt.png
pyladies/swag/tshirts/i-love-pyladies/pyladies-tshirt.svg
pyladies-2.0.4.dist-info/DESCRIPTION.rst
pyladies-2.0.4.dist-info/entry_points.txt
pyladies-2.0.4.dist-info/METADATA
pyladies-2.0.4.dist-info/metadata.json
pyladies-2.0.4.dist-info/RECORD
pyladies-2.0.4.dist-info/top_level.txt
pyladies-2.0.4.dist-info/WHEEL
