Metadata-Version: 2.0
Name: pyladies
Version: 2.0.4
Summary: Everything you need to start your own PyLadies location
Home-page: http://www.pyladies.com
Author: Lynn Root
Author-email: lynn@pyladies.com
License: Creative Commons Attribution-ShareAlike 3.0 Unported
Platform: any
Requires-Dist: Sphinx
Requires-Dist: sphinx-rtd-theme
